hw1/minority.v
`timescale 1ns / 1ps

module minority(
    input a,
    input b, 
    input c,
    output y
);
     
   assign y = a ^ b ^ c;
    
endmodule

hw1/tb2.v
`timescale 1ns/1ps

module tb2; 
  reg [2:0] a;
  
  wire y; 
  minority dut (.a(a[0]), .b(a[1]), .c(a[2]), .y(y));
  integer i;
 
  initial begin

    $dumpfile("wave2.vcd");

    $dumpvars(0, tb2);

    $monitor("t=%0t | a=%0b | b=%b | c=%b-> y=%0b", $time, a[0], a[1], a[2], y);

    for(i=0; i<8; i=i+1) begin
      a=i;
      #10;
    end
    $finish;
  end
endmodule

hw1/wave2.vcd
$date
	Tue Feb 17 12:25:03 2026
$end
$version
	Icarus Verilog
$end
$timescale
	1ps
$end
$scope module tb2 $end
$var wire 1 ! y $end
$var reg 3 " a [2:0] $end
$var integer 32 # i [31:0] $end
$scope module dut $end
$var wire 1 $ a $end
$var wire 1 % b $end
$var wire 1 & c $end
$var wire 1 ! y $end
$upscope $end
$upscope $end
$enddefinitions $end
$comment Show the parameter values. $end
$dumpall
$end
#0
$dumpvars
0&
0%
0$
b0 #
b0 "
0!
$end
#10000
1!
1$
b1 "
b1 #
#20000
0$
1%
b10 "
b10 #
#30000
0!
1$
b11 "
b11 #
#40000
1!
0$
0%
1&
b100 "
b100 #
#50000
0!
1$
b101 "
b101 #
#60000
0$
1%
b110 "
b110 #
#70000
1!
1$
b111 "
b111 #
#80000
b1000 #
