hw1/four_xor.v
`timescale 1ns / 1ps

module four_xor(
    input [3:0]a,
    output y
);
     
   assign y = ^a;
    
endmodule

hw1/tb.v
`timescale 1ns/1ps

module tb; //module header -> needs ; after
  //"registers" represent storage elements in hardware, can be assigned values
  reg [3:0] a;
  //cannot assign to wire inside 'always' block, which is used to describe continuous behavior of hardware
  //procedural block 'always'= infinite loop that executes sequential statements if triggered
  wire y; //representing physical connection in hardware
  //dut = "design under test"
  four_xor dut (.a(a), .y(y));
  integer i;
  //initial blocks execute only once at beginning t=0
  initial begin
    // dump into VCD file BEFORE any time passes
    $dumpfile("wave.vcd");
    //dumvars(level, scope) -> 0 = all var in & below scope
    $dumpvars(0, tb);
    //$display prints when explicitly called, BUT monitor prints when VARS CHANGE
    $monitor("t=%0t | a=%0b -> y=%0b", $time, a, y);

    for(i=0; i<16; i=i+1) begin
      a=i;
      #10;
    end
    $finish;
  end
endmodule //keyword to terminate module

hw1/wave.vcd
$date
	Mon Feb 16 16:05:21 2026
$end
$version
	Icarus Verilog
$end
$timescale
	1ps
$end
$scope module tb $end
$var wire 1 ! y $end
$var reg 4 " a [3:0] $end
$var integer 32 # i [31:0] $end
$scope module dut $end
$var wire 4 $ a [3:0] $end
$var wire 1 ! y $end
$upscope $end
$upscope $end
$enddefinitions $end
$comment Show the parameter values. $end
$dumpall
$end
#0
$dumpvars
b0 $
b0 #
b0 "
0!
$end
#10000
1!
b1 "
b1 $
b1 #
#20000
b10 "
b10 $
b10 #
#30000
0!
b11 "
b11 $
b11 #
#40000
1!
b100 "
b100 $
b100 #
#50000
0!
b101 "
b101 $
b101 #
#60000
b110 "
b110 $
b110 #
#70000
1!
b111 "
b111 $
b111 #
#80000
b1000 "
b1000 $
b1000 #
#90000
0!
b1001 "
b1001 $
b1001 #
#100000
b1010 "
b1010 $
b1010 #
#110000
1!
b1011 "
b1011 $
b1011 #
#120000
0!
b1100 "
b1100 $
b1100 #
#130000
1!
b1101 "
b1101 $
b1101 #
#140000
b1110 "
b1110 $
b1110 #
#150000
0!
b1111 "
b1111 $
b1111 #
#160000
b10000 #
