hw2/t_using_d.v
`timescale 1ns / 1ps
//dFF has input clk, output Q+ = D
//tFF has input clk, output Q+ = ~Q
module t_using_d(
    input wire clk,
    //Q is reg since driven by always in DUT
    output reg Q
);
//executes once, initializes Q to 0 to prevent X
initial Q = 0;
wire D = ~Q;
always @(posedge clk) begin
    Q <= D;
end
endmodule

hw2/tb1.v
`timescale 1ns/1ps

module tb1; 
  reg clk=0;
  //Q is wire in tb, but reg in module 
  //(driven by always in DUT, driven by DUT in tb)
  wire Q;
  
  t_using_d dut(.clk(clk), .Q(Q));

  always #5 clk = ~clk; //5ns low, 5ns high
  integer i;
  initial begin
    $dumpfile("wave1.vcd");
    $dumpvars(0, tb1);
    $monitor("t=%0t | Q=%b", $time, Q);
    for(i=0; i<8; i=i+1) begin
      @(posedge clk);
    end
    $finish;
  end
endmodule

hw2/wave1.vcd
$date
	Thu Feb 26 16:35:32 2026
$end
$version
	Icarus Verilog
$end
$timescale
	1ps
$end
$scope module tb1 $end
$var wire 1 ! Q $end
$var reg 1 " clk $end
$var integer 32 # i [31:0] $end
$scope module dut $end
$var wire 1 $ D $end
$var wire 1 " clk $end
$var reg 1 ! Q $end
$upscope $end
$upscope $end
$enddefinitions $end
$comment Show the parameter values. $end
$dumpall
$end
#0
$dumpvars
1$
b0 #
0"
0!
$end
#5000
0$
1!
b1 #
1"
#10000
0"
#15000
1$
0!
b10 #
1"
#20000
0"
#25000
0$
1!
b11 #
1"
#30000
0"
#35000
1$
0!
b100 #
1"
#40000
0"
#45000
0$
1!
b101 #
1"
#50000
0"
#55000
1$
0!
b110 #
1"
#60000
0"
#65000
0$
1!
b111 #
1"
#70000
0"
#75000
1$
0!
b1000 #
1"
