hw2/mod_8_gray.v
`timescale 1ns / 1ps
//matches highest bit significance of input to output val
module mod_8_gray(
    input clk,
    output reg [2:0]Q
);
initial Q=0;
reg [2:0]count=0;   
always @(posedge clk) begin
    count = (count+1)%8;
    Q[2] = count[2];
    Q[1] = count[2] ^ count[1];
    Q[0] = count[1] ^ count[0];
end
endmodule

hw2/tb3.v
`timescale 1ns/1ps

module tb3; 
  reg clk=0;
  //Q is wire in tb, but reg in module 
  //(driven by always in DUT, driven by DUT in tb)
  wire [2:0]Q;
  
  mod_8_gray dut(.clk(clk), .Q(Q));

  always #5 clk = ~clk; //5ns low, 5ns high
  integer i;
  integer count;
  initial begin
    $dumpfile("wave3.vcd");
    $dumpvars(0, tb3);
    $monitor("t=%0t | gray#=%d | Q=%b", $time, count, Q);
    for(i=0; i<16; i=i+1) begin
      count=i%8;
      @(posedge clk);
    end
    $finish;
  end
endmodule

hw2/wave3.vcd
$date
	Thu Feb 26 19:10:57 2026
$end
$version
	Icarus Verilog
$end
$timescale
	1ps
$end
$scope module tb3 $end
$var wire 3 ! Q [2:0] $end
$var reg 1 " clk $end
$var integer 32 # count [31:0] $end
$var integer 32 $ i [31:0] $end
$scope module dut $end
$var wire 1 " clk $end
$var reg 3 % Q [2:0] $end
$var reg 3 & count [2:0] $end
$upscope $end
$upscope $end
$enddefinitions $end
$comment Show the parameter values. $end
$dumpall
$end
#0
$dumpvars
b0 &
b0 %
b0 $
b0 #
0"
b0 !
$end
#5000
b1 !
b1 %
b1 &
b1 #
b1 $
1"
#10000
0"
#15000
b10 #
b10 $
b11 !
b11 %
b10 &
1"
#20000
0"
#25000
b10 !
b10 %
b11 &
b11 #
b11 $
1"
#30000
0"
#35000
b100 #
b100 $
b110 !
b110 %
b100 &
1"
#40000
0"
#45000
b111 !
b111 %
b101 &
b101 #
b101 $
1"
#50000
0"
#55000
b110 #
b110 $
b101 !
b101 %
b110 &
1"
#60000
0"
#65000
b100 !
b100 %
b111 &
b111 #
b111 $
1"
#70000
0"
#75000
b0 #
b1000 $
b0 !
b0 %
b0 &
1"
#80000
0"
#85000
b1 !
b1 %
b1 &
b1 #
b1001 $
1"
#90000
0"
#95000
b10 #
b1010 $
b11 !
b11 %
b10 &
1"
#100000
0"
#105000
b10 !
b10 %
b11 &
b11 #
b1011 $
1"
#110000
0"
#115000
b100 #
b1100 $
b110 !
b110 %
b100 &
1"
#120000
0"
#125000
b111 !
b111 %
b101 &
b101 #
b1101 $
1"
#130000
0"
#135000
b110 #
b1110 $
b101 !
b101 %
b110 &
1"
#140000
0"
#145000
b100 !
b100 %
b111 &
b111 #
b1111 $
1"
#150000
0"
#155000
b10000 $
b0 !
b0 %
b0 &
1"
