hw2/fsm.v
`timescale 1ns / 1ps
module fsm (
    input  wire clk,
    input  wire A,
    input  wire B,
    output wire Z
);
    reg S;

    //D-FF = state register: store An-1
    always @(posedge clk) begin
        //at edge, RHS A is evaluated, state update is only SCHEDULED
        //S will not change immediately because NONBLOCKING ASSINGMENT
        S <= A;
    end
    //output logic (verilog is concurrent, not sequential)
    //Z equation still uses the old S
    assign Z = (~B * (A * S)) | (B * (A + S));

endmodule

hw2/tb_fsm.v
`timescale 1ns/1ps

module tb_fsm;

  reg  clk = 0;
  reg  [1:0] ab=0;
  wire Z;

  // Instantiate DUT
  fsm dut (
    .clk(clk),
    .A(ab[0]),
    .B(ab[1]),
    .Z(Z)
  );

  reg prevA=0; //assuming initial An-1 = 0
  // 10ns period clock
  always #5 clk = ~clk;
  //store prevA at posedge
  always @(posedge clk) begin
        prevA <=ab[0];
      end
  integer i;
  initial begin
    $dumpfile("wave4.vcd");
    $dumpvars(0, tb_fsm);
    $monitor("t=%0t | AB=%b | prevA=%b | Z=%b", $time, ab, prevA, Z);
    for(i=0; i<8; i=i+1) begin
      @(negedge clk);
      ab <= i; //updates ab at neg edge
    end

    //what does this do, why are there two posedges?
    @(posedge clk);
    #1
    $finish;
  end

endmodule

hw2/wave4.vcd
$date
	Thu Feb 26 23:13:25 2026
$end
$version
	Icarus Verilog
$end
$timescale
	1ps
$end
$scope module tb_fsm $end
$var wire 1 ! Z $end
$var reg 2 " ab [1:0] $end
$var reg 1 # clk $end
$var reg 1 $ prevA $end
$var integer 32 % i [31:0] $end
$scope module dut $end
$var wire 1 & A $end
$var wire 1 ' B $end
$var wire 1 ! Z $end
$var wire 1 # clk $end
$var reg 1 ( S $end
$upscope $end
$upscope $end
$enddefinitions $end
$comment Show the parameter values. $end
$dumpall
$end
#0
$dumpvars
x(
0'
0&
b0 %
0$
0#
b0 "
x!
$end
#5000
0!
0(
1#
#10000
b1 %
0#
#15000
1#
#20000
1&
b1 "
b10 %
0#
#25000
1!
1(
1$
1#
#30000
0&
1'
b10 "
b11 %
0#
#35000
0!
0$
0(
1#
#40000
1!
1&
b11 "
b100 %
0#
#45000
0!
1(
1$
1#
#50000
0&
0'
b0 "
b101 %
0#
#55000
0$
0(
1#
#60000
1&
b1 "
b110 %
0#
#65000
1!
1(
1$
1#
#70000
0&
1'
b10 "
b111 %
0#
#75000
0!
0$
0(
1#
#80000
1!
1&
b11 "
b1000 %
0#
#85000
0!
1(
1$
1#
